fastapi_oidc_auth/__init__.py
fastapi_oidc_auth/auth.py
fastapi_oidc_auth/exceptions.py
prokie_fastapi_oidc_auth-0.2.0.dist-info/LICENSE
prokie_fastapi_oidc_auth-0.2.0.dist-info/METADATA
prokie_fastapi_oidc_auth-0.2.0.dist-info/WHEEL
prokie_fastapi_oidc_auth-0.2.0.dist-info/top_level.txt
prokie_fastapi_oidc_auth-0.2.0.dist-info/RECORD
