Metadata-Version: 2.1
Name: prokie-fastapi-oidc-auth
Version: 0.2.0
Summary: OIDC auth in fastapi using a decorator
Author-email: Matthias Osswald <m@osswald.li>, Pontus Thomsson <p@gmail.com>
License: GPL-3.0-or-later
Classifier: Programming Language :: Python :: 3
Requires-Python: >=3.10
License-File: LICENSE
Requires-Dist: fastapi
Requires-Dist: PyJWT[crypto]
Requires-Dist: requests
Requires-Dist: uvicorn
Provides-Extra: development
Requires-Dist: black ==23.7.0 ; extra == 'development'
Requires-Dist: mypy ==1.5.1 ; extra == 'development'
Requires-Dist: nox ==2023.4.22 ; extra == 'development'
Requires-Dist: pytest ==7.4.1 ; extra == 'development'
Requires-Dist: pytest-cov ==4.1.0 ; extra == 'development'
Requires-Dist: types-requests ==2.31.0.2 ; extra == 'development'
Requires-Dist: selenium ==4.12.0 ; extra == 'development'
Requires-Dist: ruff ==0.0.287 ; extra == 'development'
Requires-Dist: chromedriver-py ==116.0.5845.96 ; extra == 'development'
